{
    "result":[{
        "id":1,
        "name":"小于18",
        "text":"您的BMI身体质量指数为XX.XX（BMI低于18为轻体重状态），推测您在日常生活中可能营养不良，容易引发贫血、易疲劳、体力不支等症状。建议您及时补充身体营养元素，合理调整膳食结构，同时辅以运动，增强自身免疫力。"
    },{
        "id":2,
        "name":"18-24.99",
        "text":"您的BMI身体质量指数为XX.XX（BMI的标准值范围为18-24.99），属于理想情况，希望您继续保持下去！"
    },{
        "id":3,
        "name":"25-27.99",
        "text":"您的BMI身体质量指数为XX.XX（BMI大于等于25为偏重状态），推测您在日常生活中可能新陈代谢紊乱，容易导致高血压、高血脂、高血糖（也就是俗称的“三高”问题），疲乏无力、呼吸急促、呼吸困难、关节酸疼等病症。建议您及时减重，远离慢性疾病的困扰，同时调整膳食结构，补充促进代谢、帮助减脂的营养元素，同时辅以运动，保养关节，增强自身免疫力。"
    },{
        "id":4,
        "name":"28以上",
        "text":"您的BMI身体质量指数为XX.XX（BMI大于等于28为肥胖状态），建议您管控自己的体重并及时咨询医生。"
    }],
    "status":0,
    "message":"自测静态数据"
}
